utilityapp/__init__.py
utilityapp/app.log
utilityapp/app.py
utilityapp/requirements.txt
utilityapp/run.bat
utilityapp/archive/book3.xlsx
utilityapp/archive/testdatatable.xlsx
utilityapp/logs/app_20241220_170308.log
utilityapp/logs/app_20241220_170337.log
utilityapp/logs/app_20241220_170338.log
utilityapp/logs/app_20241220_170412.log
utilityapp/logs/app_20241220_170413.log
utilityapp/logs/app_20241220_170724.log
utilityapp/logs/app_20241220_170725.log
utilityapp/static/style.css
utilityapp/static/images/logo.png
utilityapp/templates/done.html
utilityapp/templates/index.html
utilityapp/uploads/testdatatable.xlsx
QapitolApp-0.9.0.dist-info/METADATA
QapitolApp-0.9.0.dist-info/WHEEL
QapitolApp-0.9.0.dist-info/entry_points.txt
QapitolApp-0.9.0.dist-info/top_level.txt
QapitolApp-0.9.0.dist-info/RECORD
